trakt/__init__.py
trakt/client.py
trakt/helpers.py
trakt/hooks.py
trakt/sphinxext.py
trakt/version.py
trakt/core/__init__.py
trakt/core/configuration.py
trakt/core/context_collection.py
trakt/core/context_stack.py
trakt/core/emitter.py
trakt/core/errors.py
trakt/core/exceptions.py
trakt/core/helpers.py
trakt/core/http.py
trakt/core/keylock.py
trakt/core/pagination.py
trakt/core/request.py
trakt/interfaces/__init__.py
trakt/interfaces/auth.py
trakt/interfaces/calendars.py
trakt/interfaces/scrobble.py
trakt/interfaces/search.py
trakt/interfaces/base/__init__.py
trakt/interfaces/lists/__init__.py
trakt/interfaces/movies/__init__.py
trakt/interfaces/oauth/__init__.py
trakt/interfaces/oauth/device.py
trakt/interfaces/oauth/pin.py
trakt/interfaces/shows/__init__.py
trakt/interfaces/sync/__init__.py
trakt/interfaces/sync/collection.py
trakt/interfaces/sync/history.py
trakt/interfaces/sync/playback.py
trakt/interfaces/sync/ratings.py
trakt/interfaces/sync/watched.py
trakt/interfaces/sync/watchlist.py
trakt/interfaces/sync/core/__init__.py
trakt/interfaces/sync/core/mixins.py
trakt/interfaces/users/__init__.py
trakt/interfaces/users/following.py
trakt/interfaces/users/friends.py
trakt/interfaces/users/history.py
trakt/interfaces/users/profile.py
trakt/interfaces/users/ratings.py
trakt/interfaces/users/settings.py
trakt/interfaces/users/watched.py
trakt/interfaces/users/watchlist.py
trakt/interfaces/users/lists/__init__.py
trakt/interfaces/users/lists/list_.py
trakt/mapper/__init__.py
trakt/mapper/comment.py
trakt/mapper/list.py
trakt/mapper/list_item.py
trakt/mapper/progress.py
trakt/mapper/search.py
trakt/mapper/summary.py
trakt/mapper/sync.py
trakt/mapper/user.py
trakt/mapper/core/__init__.py
trakt/mapper/core/base.py
trakt/objects/__init__.py
trakt/objects/comment.py
trakt/objects/episode.py
trakt/objects/media.py
trakt/objects/movie.py
trakt/objects/person.py
trakt/objects/progress.py
trakt/objects/rating.py
trakt/objects/season.py
trakt/objects/show.py
trakt.py-4.4.0.dist-info/AUTHORS
trakt.py-4.4.0.dist-info/LICENSE.rst
trakt.py-4.4.0.dist-info/METADATA
trakt.py-4.4.0.dist-info/WHEEL
trakt.py-4.4.0.dist-info/pbr.json
trakt.py-4.4.0.dist-info/top_level.txt
trakt.py-4.4.0.dist-info/RECORD
