Metadata-Version: 2.1
Name: trakt.py
Version: 4.4.0
Summary: Python interface for the Trakt.tv API
Home-page: https://github.com/fuzeman/trakt.py
Author: Dean Gardiner
Author-email: me@dgardiner.net
License: MIT
Keywords: trakt.tv,api,client
Platform: any
Classifier: Development Status :: 5 - Production/Stable
Classifier: Intended Audience :: Developers
Classifier: License :: OSI Approved :: MIT License
Classifier: Operating System :: OS Independent
Classifier: Programming Language :: Python
Classifier: Programming Language :: Python :: 2
Classifier: Programming Language :: Python :: 2.7
Classifier: Programming Language :: Python :: 3
Classifier: Programming Language :: Python :: 3.5
Classifier: Programming Language :: Python :: 3.6
Classifier: Programming Language :: Python :: 3.7
Classifier: Programming Language :: Python :: 3.8
Classifier: Programming Language :: Python :: Implementation :: CPython
Classifier: Programming Language :: Python :: Implementation :: PyPy
Classifier: Topic :: Software Development :: Libraries
Requires-Dist: arrow (<2.0.0,>=0.15.0)
Requires-Dist: requests (!=2.16.0,<3.0.0,>=2.4.0)
Requires-Dist: six (<2.0.0,>=1.10.0)
